papercut_xml_webservices_api/__init__.py
papercut_xml_webservices_api/papercut_xml_webservices_api.py
papercut_xml_webservices_api/ServerCommand/Const.py
papercut_xml_webservices_api/ServerCommand/Proxy.py
papercut_xml_webservices_api/ServerCommand/ServerComandProxy.py
papercut_xml_webservices_api/ServerCommand/ServerCommandProxy.py
papercut_xml_webservices_api/ServerCommand/__init__.py
papercut_xml_webservices_api/ServerCommand/exceptions.py
papercut_xml_webservices_api-0.2.5.dist-info/AUTHORS.md
papercut_xml_webservices_api-0.2.5.dist-info/LICENSE
papercut_xml_webservices_api-0.2.5.dist-info/METADATA
papercut_xml_webservices_api-0.2.5.dist-info/WHEEL
papercut_xml_webservices_api-0.2.5.dist-info/top_level.txt
papercut_xml_webservices_api-0.2.5.dist-info/zip-safe
papercut_xml_webservices_api-0.2.5.dist-info/RECORD
