Metadata-Version: 2.1
Name: papercut-xml-webservices-api
Version: 0.2.5
Summary: PaperCut NG/MF server's API uses XML-RPC. This library utilizes Python's [stable XMLRPC library
Home-page: https://github.com/safehome_jdev/PaperCutSoftware
Author: Jordan Reyes
Author-email: Jordan Reyes <jreyes@safehomedev.com>
License: MIT license
Project-URL: Homepage, https://github.com/safehome-jdev/PaperCutSoftware/api/papercut_xml_webservices_api
Project-URL: Bug Tracker, https://github.com/safehome-jdev/PaperCutSoftware/issues
Keywords: papercut,xml,api,NG,MF
Classifier: Development Status :: 2 - Pre-Alpha
Classifier: Intended Audience :: Developers
Classifier: License :: OSI Approved :: MIT License
Classifier: Natural Language :: English
Classifier: Programming Language :: Python :: 3.8
Classifier: Programming Language :: Python :: 3.10
Classifier: Programming Language :: Python :: 3.11
Requires-Python: >=3.8
License-File: LICENSE
License-File: AUTHORS.md
Requires-Dist: importlib-metadata ; python_version < "3.8"
